{
    "version": "2.0.dev7",
    "description": "NifSkope is a tool for opening and editing the NetImmerse file format (NIF)",
    "homepage": "https://github.com/niftools/nifskope",
    "license": "NIFSKOPE LICENSE",
    "architecture": {
        "64bit": {
            "url": "https://github.com/niftools/nifskope/releases/download/v2.0.dev7/NifSkope_2_0_2018-02-22-x64.7z",
            "hash": "3f1e1f3cdedb4d3547293d699affb67c1220b74b63d09012ac1db5d6e12c7070",
        }
    },
    "extract_dir": "NifSkope_2_0_2018-02-22-x64"    
    "bin": "NifScope.exe",
    "checkver": "github"
}
